[
  {
    "word": "apple"
  },
  {
    "word": "ball"
  },
  {
    "word": "cat"
  },
  {
    "word": "dog"
  },
  {
    "word": "egg"
  },
  {
    "word": "fish"
  },
  {
    "word": "hat"
  },
  {
    "word": "ink"
  },
  {
    "word": "jet"
  },
  {
    "word": "key"
  },
  {
    "word": "leaf"
  },
  {
    "word": "moon"
  },
  {
    "word": "nose"
  },
  {
    "word": "oven"
  },
  {
    "word": "pen"
  },
  {
    "word": "queen"
  },
  {
    "word": "rain"
  },
  {
    "word": "sun"
  },
  {
    "word": "tree"
  },
  {
    "word": "umbrella"
  },
  {
    "word": "van"
  },
  {
    "word": "window"
  },
  {
    "word": "xylophone"
  },
  {
    "word": "yacht"
  },
  {
    "word": "zebra"
  }
]
